gns_helper/__init__.py
gns_helper/app_routes.py
gns_helper/config.py
gns_helper/constants.py
gns_helper/custom_decorators.py
gns_helper/set_db_name.py
gns_helper/table_operations.py
gns_helper/user_auth.py
gns_helper/views_helper_functions.py
gns_helper/wifi_functions.py
gns_helper/zpl_label_designer.py
gns_helper-0.5.dist-info/LICENSE
gns_helper-0.5.dist-info/METADATA
gns_helper-0.5.dist-info/WHEEL
gns_helper-0.5.dist-info/top_level.txt
gns_helper-0.5.dist-info/RECORD
